b2accessdeprovisioning/__init__.py
b2accessdeprovisioning/configparser.py
b2accessdeprovisioning/monitor.py
b2accessdeprovisioning/notifier.py
b2accessdeprovisioning/user.py
b2accessdeprovisioning-0.9.1.dist-info/DESCRIPTION.rst
b2accessdeprovisioning-0.9.1.dist-info/METADATA
b2accessdeprovisioning-0.9.1.dist-info/RECORD
b2accessdeprovisioning-0.9.1.dist-info/WHEEL
b2accessdeprovisioning-0.9.1.dist-info/metadata.json
b2accessdeprovisioning-0.9.1.dist-info/top_level.txt
