Metadata-Version: 2.0
Name: b2accessdeprovisioning
Version: 0.9.1
Summary: B2ACCESS account (de)provisioning tool
Home-page: https://eudat-b2access.github.io/b2access-deprovisioning
Author: Nicolas Liampotis
Author-email: nliam@grnet.gr
License: Apache License 2.0
Download-URL: https://github.com/EUDAT-B2ACCESS/b2access-deprovisioning
Keywords: B2ACCESS account (de)provisioning tool
Platform: UNKNOWN
Classifier: Development Status :: 4 - Beta
Classifier: Programming Language :: Python :: 2
Classifier: Programming Language :: Python :: 2.6
Classifier: Programming Language :: Python :: 2.7
Classifier: License :: OSI Approved :: Apache Software License
Classifier: Intended Audience :: Developers
Classifier: Topic :: Software Development :: Libraries :: Python Modules
Requires-Python: >=2.6,<2.8
Requires-Dist: unityapiclient
Requires-Dist: PyYAML
